[
null,
{"id":1,"expanded":true,"name":"Mirannuk","order":1,"parentId":0,"scrollX":11479.5,"scrollY":1989.5},
{"id":2,"expanded":true,"name":"Mirannuk Caves","order":3,"parentId":3,"scrollX":5335.5,"scrollY":1829.5},
{"id":3,"expanded":true,"name":"Mirannuk Caves Transfer","order":2,"parentId":1,"scrollX":808.5,"scrollY":1126.5},
{"id":4,"expanded":true,"name":"Mirannuk Caves 2nd Floor","order":4,"parentId":2,"scrollX":2263.5,"scrollY":506.5},
{"id":5,"expanded":true,"name":"Mirannuk Caves 3rd Floor","order":5,"parentId":4,"scrollX":1865.5,"scrollY":409.5},
{"id":6,"expanded":false,"name":"Hollow Woods","order":6,"parentId":5,"scrollX":5335.5,"scrollY":749.5},
{"id":7,"expanded":false,"name":"Mirannuk Caves to Hollow Woods","order":7,"parentId":5,"scrollX":1948.5,"scrollY":469.5},
{"id":8,"expanded":false,"name":"Trader's Shack","order":8,"parentId":1,"scrollX":811,"scrollY":444},
{"id":9,"expanded":false,"name":"Shack1","order":9,"parentId":1,"scrollX":809,"scrollY":444},
{"id":10,"expanded":false,"name":"Shack2","order":10,"parentId":1,"scrollX":809,"scrollY":444},
{"id":11,"expanded":false,"name":"Shack3","order":11,"parentId":1,"scrollX":816.5,"scrollY":417.5},
{"id":12,"expanded":false,"name":"Guard Barracks","order":12,"parentId":1,"scrollX":816.5,"scrollY":417.5},
{"id":13,"expanded":true,"name":"Hollow Woods South","order":13,"parentId":1,"scrollX":816,"scrollY":624},
{"id":14,"expanded":false,"name":"Hollow Woods East","order":22,"parentId":0,"scrollX":803,"scrollY":436},
{"id":15,"expanded":false,"name":"Creed","order":23,"parentId":0,"scrollX":808.5,"scrollY":1050.5},
{"id":16,"expanded":false,"name":"Ruins area","order":24,"parentId":0,"scrollX":803,"scrollY":1996},
{"id":17,"expanded":true,"name":"Turitian Swamps North","order":25,"parentId":0,"scrollX":5335.5,"scrollY":624.5},
{"id":18,"expanded":false,"name":"Inside Hut in Swamp","order":26,"parentId":17,"scrollX":811,"scrollY":444},
{"id":19,"expanded":true,"name":"Turitian Swamps Central","order":27,"parentId":17,"scrollX":808.5,"scrollY":436.5},
{"id":20,"expanded":true,"name":"Slavers Hold - 1st Floor","order":28,"parentId":19,"scrollX":1332.5,"scrollY":409.5},
{"id":21,"expanded":true,"name":"Slavers Hold - 2nd Floor","order":29,"parentId":20,"scrollX":808.5,"scrollY":409.5},
{"id":22,"expanded":true,"name":"Slavers Hold - 3rd Floor","order":30,"parentId":21,"scrollX":808.5,"scrollY":426.5},
{"id":23,"expanded":true,"name":"Slavers Hold 4th Floor","order":31,"parentId":22,"scrollX":808.5,"scrollY":446.5},
{"id":24,"expanded":false,"name":"Liege's Quarters","order":33,"parentId":22,"scrollX":816.5,"scrollY":417.5},
{"id":25,"expanded":false,"name":"Hold's Vault","order":32,"parentId":23,"scrollX":816.5,"scrollY":417.5},
{"id":26,"expanded":false,"name":"West Cabin","order":15,"parentId":1,"scrollX":816.5,"scrollY":417.5},
{"id":27,"expanded":true,"name":"Manawrought Waste - Intro","order":34,"parentId":0,"scrollX":808.5,"scrollY":1230.5},
{"id":28,"expanded":true,"name":"Manawrought Waste - Ari Tradepost","order":35,"parentId":27,"scrollX":808.5,"scrollY":409.5},
{"id":29,"expanded":true,"name":"Manawrought Waste - North","order":36,"parentId":28,"scrollX":5312.5,"scrollY":2432.5},
{"id":30,"expanded":true,"name":"Manawrought Waste - Center","order":37,"parentId":29,"scrollX":5335.5,"scrollY":1802.5},
{"id":31,"expanded":true,"name":"Manawrought Waste - East","order":38,"parentId":30,"scrollX":808.5,"scrollY":624.5},
{"id":32,"expanded":true,"name":"Manawrought Waste - Northeast","order":39,"parentId":31,"scrollX":5335.5,"scrollY":409.5},
{"id":33,"expanded":true,"name":"Makani Woods -East","order":16,"parentId":1,"scrollX":816.5,"scrollY":624.5},
{"id":34,"expanded":true,"name":"Makani Woods - Middle","order":17,"parentId":33,"scrollX":808.5,"scrollY":409.5},
{"id":35,"expanded":true,"name":"Makani Woods - South","order":18,"parentId":34,"scrollX":976,"scrollY":624},
{"id":36,"expanded":true,"name":"Makani Woods - North","order":19,"parentId":35,"scrollX":1566,"scrollY":912},
{"id":37,"expanded":false,"name":"Makani Woods - Siki Village","order":20,"parentId":36,"scrollX":2263.5,"scrollY":409.5},
{"id":38,"expanded":true,"name":"Makani Woods - West","order":21,"parentId":33,"scrollX":816.5,"scrollY":411.5},
{"id":39,"expanded":false,"name":"Furaji Wetlands","order":14,"parentId":13,"scrollX":11472.5,"scrollY":624.5},
{"id":40,"expanded":true,"name":"Manawrought Caves - 1st Floor","order":47,"parentId":31,"scrollX":808.5,"scrollY":1126.5},
{"id":41,"expanded":true,"name":"Manawrought Caves - 2nd Floor","order":48,"parentId":40,"scrollX":2240.5,"scrollY":640.5},
{"id":42,"expanded":true,"name":"Manawrought Caves - 3rd Floor","order":49,"parentId":41,"scrollX":2238.5,"scrollY":1126.5},
{"id":43,"expanded":true,"name":"Sourfields Upper","order":50,"parentId":42,"scrollX":2263.5,"scrollY":1126.5},
{"id":44,"expanded":false,"name":"Sourfields Lower","order":51,"parentId":43,"scrollX":2263.5,"scrollY":1126.5},
{"id":45,"expanded":true,"name":"Gildur Plains","order":40,"parentId":32,"scrollX":1254.5,"scrollY":409.5},
{"id":46,"expanded":true,"name":"Gildur Plains - Mercenary Camp","order":41,"parentId":45,"scrollX":2263.5,"scrollY":409.5},
{"id":47,"expanded":true,"name":"Gildur Caves - Entrance Area","order":42,"parentId":46,"scrollX":2263.5,"scrollY":789.5},
{"id":48,"expanded":true,"name":"Gildur Caves - Closed Area","order":43,"parentId":47,"scrollX":2263.5,"scrollY":509.5},
{"id":49,"expanded":true,"name":"Gildur Caves - Open Area","order":44,"parentId":48,"scrollX":2263.5,"scrollY":409.5},
{"id":50,"expanded":true,"name":"Gildur Caves - Enemy Infested Area","order":45,"parentId":49,"scrollX":2263.5,"scrollY":519.5},
{"id":51,"expanded":false,"name":"Gildur Caves - Drowned Area","order":46,"parentId":50,"scrollX":2263.5,"scrollY":469.5}
]